Metadata-Version: 1.0
Name: torquepy
Version: 0.3.1.1
Summary: Torque library
Home-page: UNKNOWN
Author: Semen Pankratov
Author-email: sema2012r@mail.ru
License: UNKNOWN
Platform: UNKNOWN
